multicon/__init__.py
multicon-0.0.2.dist-info/METADATA
multicon-0.0.2.dist-info/WHEEL
multicon-0.0.2.dist-info/top_level.txt
multicon-0.0.2.dist-info/RECORD
