Metadata-Version: 2.1
Name: multicon
Version: 0.0.2
Summary: A tiny module for creating cascade configs
Home-page: https://github.com/qwercik/multicon
Author: Eryk Andrzejewski
Author-email: erykandrzejewski@gmail.com
License: UNKNOWN
Platform: UNKNOWN
Classifier: Programming Language :: Python :: 3
Classifier: License :: OSI Approved :: MIT License
Classifier: Operating System :: OS Independent
Requires-Python: >=3.6
